LICENSE
MANIFEST.in
README.rst
setup.cfg
setup.py
./psychohistory/__init__.py
psychohistory.egg-info/PKG-INFO
psychohistory.egg-info/SOURCES.txt
psychohistory.egg-info/dependency_links.txt
psychohistory.egg-info/requires.txt
psychohistory.egg-info/top_level.txt