Metadata-Version: 1.1
Name: psychohistory
Version: 0.0.1
Summary: Code for my dissertation.
Home-page: https://github.com/jbn/psychohistory
Author: John Bjorn Nelson
Author-email: jbn@abreka.com
License: MIT
Keywords: psychohistory,belief systems,opinion dynamics
Platform: UNKNOWN
Classifier: Development Status :: 3 - Alpha
Classifier: Intended Audience :: Science/Research
Classifier: Topic :: Scientific/Engineering :: Information Analysis
Classifier: License :: OSI Approved :: MIT License
Classifier: Programming Language :: Python :: 2.7
Classifier: Programming Language :: Python :: 3
Classifier: Programming Language :: Python :: 3.2
Classifier: Programming Language :: Python :: 3.3
Classifier: Programming Language :: Python :: 3.4
Classifier: Programming Language :: Python :: 3.5
